crudcreator/AbstractCRUDableEntityType.py
crudcreator/AbstractDescriptor.py
crudcreator/FieldOfCRUDableEntityType.py
crudcreator/Fields.py
crudcreator/Filter.py
crudcreator/Link.py
crudcreator/LinkType.py
crudcreator/OptionModel.py
crudcreator/Sentinel.py
crudcreator/__init__.py
crudcreator/exceptions.py
crudcreator/schema.py
crudcreator/adaptator/__init__.py
crudcreator/adaptator/sql/AbstractSQLEntityType.py
crudcreator/adaptator/sql/SQLColumn.py
crudcreator/adaptator/sql/SQLColumnInspector.py
crudcreator/adaptator/sql/SQLEntityTypeInterface.py
crudcreator/adaptator/sql/__init__.py
crudcreator/adaptator/sql/engine_wrapper/SQLConnectionWrapper.py
crudcreator/adaptator/sql/engine_wrapper/SQLEngineWrapper.py
crudcreator/adaptator/sql/engine_wrapper/SQLInspectorWrapper.py
crudcreator/adaptator/sql/engine_wrapper/__init__.py
crudcreator/adaptator/sql/proxy/AbstractSQLRequestProxy.py
crudcreator/adaptator/sql/proxy/SQLCreateLink.py
crudcreator/adaptator/sql/proxy/SQLFilter.py
crudcreator/adaptator/sql/proxy/SQLPagination.py
crudcreator/adaptator/sql/proxy/SQLReadFromLink.py
crudcreator/adaptator/sql/proxy/SQLRequestConstructor.py
crudcreator/adaptator/sql/proxy/SQLRequestExecutor.py
crudcreator/adaptator/sql/proxy/SQLSort.py
crudcreator/adaptator/sql/proxy/__init__.py
crudcreator/adaptator/sql/type_convertor/TypeConvertor.py
crudcreator/adaptator/sql/type_convertor/__init__.py
crudcreator/builder/CRUDableEntityBuilder.py
crudcreator/builder/SetBuilder.py
crudcreator/builder/__init__.py
crudcreator/destination/AbstractDestinationCRUDBuilder.py
crudcreator/destination/__init__.py
crudcreator/destination/rest/BulkErrorModel.py
crudcreator/destination/rest/ErrorModel.py
crudcreator/destination/rest/RESTCRUDBuilder.py
crudcreator/destination/rest/__init__.py
crudcreator/destination/rest/builder/__init__.py
crudcreator/destination/rest/builder/base.py
crudcreator/destination/rest/builder/build_bulk_update.py
crudcreator/destination/rest/builder/build_create.py
crudcreator-0.0.1.dist-info/LICENSE
crudcreator-0.0.1.dist-info/METADATA
crudcreator-0.0.1.dist-info/WHEEL
crudcreator-0.0.1.dist-info/entry_points.txt
crudcreator-0.0.1.dist-info/top_level.txt
crudcreator-0.0.1.dist-info/RECORD
