Metadata-Version: 2.1
Name: crudcreator
Version: 0.0.1
Summary: Create CRUD interfaces faster.
Classifier: Programming Language :: Python :: 3
Classifier: Operating System :: OS Independent
Classifier: Development Status :: 3 - Alpha
Classifier: Framework :: FastAPI
Classifier: Framework :: Pydantic
Classifier: License :: OSI Approved :: MIT License
License-File: LICENSE
Requires-Dist: fastapi
Requires-Dist: uvicorn
Requires-Dist: SQLAlchemy
